redeval/__init__.py
redeval/agents/__init__ .py
redeval/agents/chatbot.py
redeval/agents/conservative_human_agent.py
redeval/agents/human_agent.py
redeval/agents/rag_agent.py
redeval/evaluators/__init__.py
redeval/evaluators/answer_relevance.py
redeval/evaluators/context_relevance.py
redeval/evaluators/faithfulness.py
redeval/evaluators/metric.py
redeval/evaluators/open_ai_completion.py
redeval/evaluators/safety.py
redeval/evaluators/toxicity.py
redeval/generators/questions/adversarial_question_generator.py
redeval/generators/questions/conversational_generator.py
redeval/generators/questions/gaslighting_conversation_attack_generator.py
redeval/generators/questions/guilting_conversation_attack_generator.py
redeval/generators/questions/intimate_question_generator.py
redeval/generators/questions/open_question_generator.py
redeval/generators/questions/prompt_injection_attack_generator.py
redeval/generators/questions/regular_question_generator.py
redeval/generators/questions/research_purpose_conversation_attack_generator.py
redeval/generators/questions/social_engineering_attack_question_generator.py
redeval/generators/questions/toxic_conversational_generator.py
redeval/generators/questions/toxic_question_generator.py
redeval/llms/__init__.py
redeval/llms/llama_70b_completion.py
redeval/llms/mistral_7b_completion.py
redeval/llms/open_ai_completion.py
redeval/simulators/conservative_social_engineering_attack_simulator.py
redeval/simulators/gaslighting_simulator.py
redeval/simulators/guilting_simulator.py
redeval/simulators/performance_simulator.py
redeval/simulators/prompt_injection_attack_simulator.py
redeval/simulators/research_purpose_simulator.py
redeval/simulators/social_engineering_attack_simulator.py
redeval/simulators/toxicity_simulator.py
redeval-0.1.2.dist-info/LICENSE
redeval-0.1.2.dist-info/METADATA
redeval-0.1.2.dist-info/WHEEL
redeval-0.1.2.dist-info/RECORD
