Metadata-Version: 2.1
Name: redeval
Version: 0.1.2
Summary: Auditing and Label-free Evaluation for LLMs
Author: Christos Ziakas
Requires-Python: >=3.9,<4.0
Classifier: Programming Language :: Python :: 3
Classifier: Programming Language :: Python :: 3.9
Classifier: Programming Language :: Python :: 3.10
Classifier: Programming Language :: Python :: 3.11
Classifier: Programming Language :: Python :: 3.12
Requires-Dist: datasets (>=2.14.5,<3.0.0)
Requires-Dist: llama-index (>=0.8.40,<0.9.0)
Requires-Dist: openai (>=0.28.0,<0.29.0)
Requires-Dist: pandas (>=2.1.0,<3.0.0)
Requires-Dist: pre-commit (>=3.4.0,<4.0.0)
Requires-Dist: pytest (>=8.3.3,<9.0.0)
Requires-Dist: python-dotenv (>=1.0.0,<2.0.0)
Requires-Dist: replicate (>=0.15.4,<0.16.0)
Requires-Dist: scikit-learn (>=1.3.0,<2.0.0)
Requires-Dist: torch (>=2.1.0,<3.0.0)
Requires-Dist: torchvision (>=0.16.0,<0.17.0)
Requires-Dist: transformers (>=4.34.0,<5.0.0)
